[
  {
    "title": "[Next.js] 블로그 프로젝트 준비",
    "description": "블로그를 만들 때 고려한 것",
    "imageURL": "https://www.google.com/imgres?imgurl=https%3A%2F%2Fimages.velog.io%2Fimages%2Fjay%2Fpost%2F3a497590-d1b6-414c-9f3f-7b6c7eb18f6d%2Fimg.png&tbnid=tYH2z8wiyCJGTM&vet=12ahUKEwjivKTT6Pf_AhURNt4KHcaZB7YQMygDegUIARCUAQ..i&imgrefurl=https%3A%2F%2Fvelog.io%2F%40jay%2FNext.js-%25EB%259D%25BC%25EC%259A%25B0%25ED%258C%2585&docid=xdMORv4hbWZZ0M&w=1000&h=571&q=next.js&ved=2ahUKEwjivKTT6Pf_AhURNt4KHcaZB7YQMygDegUIARCUAQ",
    "date": "2023-06-25",
    "category": "story",
    "path": "nextjs-blog-01",
    "featured": true,
    "storyTitle": "Next.js로 블로그 만들기",
    "story": "nextjs-bolg"
  },
  {
    "title": "[Next.js] 다크모드 & 반응형",
    "description": "다크모드와 반응형을 구현해보았습니다!",
    "imageURL": "https://www.google.com/imgres?imgurl=https%3A%2F%2Fimages.velog.io%2Fimages%2Fjay%2Fpost%2F3a497590-d1b6-414c-9f3f-7b6c7eb18f6d%2Fimg.png&tbnid=tYH2z8wiyCJGTM&vet=12ahUKEwjivKTT6Pf_AhURNt4KHcaZB7YQMygDegUIARCUAQ..i&imgrefurl=https%3A%2F%2Fvelog.io%2F%40jay%2FNext.js-%25EB%259D%25BC%25EC%259A%25B0%25ED%258C%2585&docid=xdMORv4hbWZZ0M&w=1000&h=571&q=next.js&ved=2ahUKEwjivKTT6Pf_AhURNt4KHcaZB7YQMygDegUIARCUAQ",
    "date": "2023-06-26",
    "category": "story",
    "path": "nextjs-blog-02",
    "featured": true,
    "storyTitle": "Next.js로 블로그 만들기",
    "story": "nextjs-bolg"
  },
  {
    "title": "[Next.js] react-multi-carousel",
    "description": "캐러셀 라이브러리를 활용한 포스트 슬라이드 구현",
    "imageURL": "https://www.google.com/imgres?imgurl=https%3A%2F%2Fimages.velog.io%2Fimages%2Fjay%2Fpost%2F3a497590-d1b6-414c-9f3f-7b6c7eb18f6d%2Fimg.png&tbnid=tYH2z8wiyCJGTM&vet=12ahUKEwjivKTT6Pf_AhURNt4KHcaZB7YQMygDegUIARCUAQ..i&imgrefurl=https%3A%2F%2Fvelog.io%2F%40jay%2FNext.js-%25EB%259D%25BC%25EC%259A%25B0%25ED%258C%2585&docid=xdMORv4hbWZZ0M&w=1000&h=571&q=next.js&ved=2ahUKEwjivKTT6Pf_AhURNt4KHcaZB7YQMygDegUIARCUAQ",
    "date": "2023-06-27",
    "category": "story",
    "path": "nextjs-blog-03",
    "featured": false,
    "storyTitle": "Next.js로 블로그 만들기",
    "story": "nextjs-bolg"
  },
  {
    "title": "[Next.js] 메일 전송 기능 만들기",
    "description": "nodemailer를 활용한 메일 전송 기능 구현",
    "imageURL": "https://www.google.com/imgres?imgurl=https%3A%2F%2Fimages.velog.io%2Fimages%2Fjay%2Fpost%2F3a497590-d1b6-414c-9f3f-7b6c7eb18f6d%2Fimg.png&tbnid=tYH2z8wiyCJGTM&vet=12ahUKEwjivKTT6Pf_AhURNt4KHcaZB7YQMygDegUIARCUAQ..i&imgrefurl=https%3A%2F%2Fvelog.io%2F%40jay%2FNext.js-%25EB%259D%25BC%25EC%259A%25B0%25ED%258C%2585&docid=xdMORv4hbWZZ0M&w=1000&h=571&q=next.js&ved=2ahUKEwjivKTT6Pf_AhURNt4KHcaZB7YQMygDegUIARCUAQ",
    "date": "2023-06-28",
    "category": "story",
    "path": "nextjs-blog-04",
    "featured": false,
    "storyTitle": "Next.js로 블로그 만들기",
    "story": "nextjs-bolg"
  },
  {
    "title": "[Next.js] 마크다운 뷰어 사용하기",
    "description": "react-markdown과 remark-gfm을 사용해 마크다운 사용하기",
    "imageURL": "https://www.google.com/imgres?imgurl=https%3A%2F%2Fimages.velog.io%2Fimages%2Fjay%2Fpost%2F3a497590-d1b6-414c-9f3f-7b6c7eb18f6d%2Fimg.png&tbnid=tYH2z8wiyCJGTM&vet=12ahUKEwjivKTT6Pf_AhURNt4KHcaZB7YQMygDegUIARCUAQ..i&imgrefurl=https%3A%2F%2Fvelog.io%2F%40jay%2FNext.js-%25EB%259D%25BC%25EC%259A%25B0%25ED%258C%2585&docid=xdMORv4hbWZZ0M&w=1000&h=571&q=next.js&ved=2ahUKEwjivKTT6Pf_AhURNt4KHcaZB7YQMygDegUIARCUAQ",
    "date": "2023-06-29",
    "category": "story",
    "path": "nextjs-blog-05",
    "featured": false,
    "storyTitle": "Next.js로 블로그 만들기",
    "story": "nextjs-bolg"
  }
]
